{
    "ret": true,
    "data" : {
        "list":[{
            "id":"0001",
            "imgUrl": "http://img1.qunarzz.com/sight/p0/1409/19/adca619faaab0898245dc4ec482b5722.jpg_140x140_80f63803.jpg",
            "title":"[配无线耳麦]天安门 + 故宫*赠珍宝馆 + 八达岭长城 + 鸟巢一日游",
            "sold":"556",
            "price":"148"
        },
        {
            "id":"0002",
            "imgUrl": "http://img1.qunarzz.com/sight/p0/1409/19/adca619faaab0898245dc4ec482b5722.jpg_140x140_80f63803.jpg",
            "title":"[配无线耳麦]天安门 + 故宫*赠珍宝馆 + 八达岭长城 + 鸟巢一日游",
            "sold":"1556",
            "price":"148"
        },
        {
            "id":"0003",
            "imgUrl": "http://img1.qunarzz.com/sight/p0/1409/19/adca619faaab0898245dc4ec482b5722.jpg_140x140_80f63803.jpg",
            "title":"[配无线耳麦]天安门 + 故宫*赠珍宝馆 + 八达岭长城 + 鸟巢一日游",
            "sold":"2556",
            "price":"148"
        },
        {
            "id":"0004",
            "imgUrl": "http://img1.qunarzz.com/sight/p0/1409/19/adca619faaab0898245dc4ec482b5722.jpg_140x140_80f63803.jpg",
            "title":"[配无线耳麦]天安门 + 故宫*赠珍宝馆 + 八达岭长城 + 鸟巢一日游",
            "sold":"3556",
            "price":"148"
        },
        {
            "id":"0005",
            "imgUrl": "http://img1.qunarzz.com/sight/p0/1409/19/adca619faaab0898245dc4ec482b5722.jpg_140x140_80f63803.jpg",
            "title":"[配无线耳麦]天安门 + 故宫*赠珍宝馆 + 八达岭长城 + 鸟巢一日游",
            "sold":"4556",
            "price":"148"
        },
        {
            "id":"0006",
            "imgUrl": "http://img1.qunarzz.com/sight/p0/1409/19/adca619faaab0898245dc4ec482b5722.jpg_140x140_80f63803.jpg",
            "title":"[配无线耳麦]天安门 + 故宫*赠珍宝馆 + 八达岭长城 + 鸟巢一日游",
            "sold":"256",
            "price":"148"
        },
        {
            "id":"0006",
            "imgUrl": "http://img1.qunarzz.com/sight/p0/1409/19/adca619faaab0898245dc4ec482b5722.jpg_140x140_80f63803.jpg",
            "title":"[配无线耳麦]天安门 + 故宫*赠珍宝馆 + 八达岭长城 + 鸟巢一日游",
            "sold":"256",
            "price":"148"
        }]
    }
}